<?xml version="1.0"?>

<ruleset name="Basic Velocity"
    xmlns="http://pmd.sourceforge.net/ruleset/2.0.0"
    xmlns:xsi="http://www.w3.org/2001/XMLSchema-instance"
    xsi:schemaLocation="http://pmd.sourceforge.net/ruleset/2.0.0 https://pmd.sourceforge.io/ruleset_2_0_0.xsd">

  <description>
The Basic Velocity ruleset contains basic rules for Apache Velocity pages.
  </description>

    <rule ref="category/vm/design.xml/AvoidDeeplyNestedIfStmts" deprecated="true" />
    <rule ref="category/vm/design.xml/CollapsibleIfStatements" deprecated="true" />
    <rule ref="category/vm/design.xml/ExcessiveTemplateLength" deprecated="true" />
    <rule ref="category/vm/design.xml/NoInlineJavaScript" deprecated="true" />
    <rule ref="category/vm/design.xml/NoInlineStyles" deprecated="true" />

    <rule ref="category/vm/bestpractices.xml/AvoidReassigningParameters" deprecated="true" />
    <rule ref="category/vm/bestpractices.xml/UnusedMacroParameter" deprecated="true" />

    <rule ref="category/vm/errorprone.xml/EmptyForeachStmt" deprecated="true" />
    <rule ref="category/vm/errorprone.xml/EmptyIfStmt" deprecated="true" />

</ruleset>
