<?xml version="1.0"?>

<ruleset name="new_for_0_7">
  <description>
These are new ones for 0.7
  </description>


 <rule name="UnnecessaryCast"
        message="Avoid unnecessary casts"
        class="net.sourceforge.pmd.rules.UnnecessaryCastRule">
    <description>
A variable is casted to one of its supertypes or interfaces.  Usually
indicates that the programmer is not clear on the class structure they
are working with.
    </description>

    <example>
<![CDATA[
public Collection doSomething() { 
  List list = new ArrayList();

  return (Collection) list; // Unnecessary Cast
}
]]>
    </example>
  </rule>

</ruleset>



